MQTTLibrary/MQTTKeywords.py
MQTTLibrary/__init__.py
MQTTLibrary/version.py
robotframework_mqttlibrary-0.7.1.post3.dist-info/LICENSE.txt
robotframework_mqttlibrary-0.7.1.post3.dist-info/METADATA
robotframework_mqttlibrary-0.7.1.post3.dist-info/WHEEL
robotframework_mqttlibrary-0.7.1.post3.dist-info/top_level.txt
robotframework_mqttlibrary-0.7.1.post3.dist-info/RECORD
