Metadata-Version: 1.1
Name: robotframework-mqttlibrary
Version: 0.7.1.post3
Summary: MQTT Keyword Library Robot Framework
Home-page: https://github.com/randomsync/robotframework-mqttlibrary
Author: Gaurav Gupta
Author-email: gaurav@randomsync.net
License: Apache License 2.0
Keywords: robotframework testing testautomation mqtt
Platform: UNKNOWN
Classifier: Development Status :: 3 - Alpha
Classifier: License :: OSI Approved :: Apache Software License
Classifier: Programming Language :: Python :: 2.7
Classifier: Programming Language :: Python :: 3.7
Classifier: Topic :: Software Development :: Testing
